git2py/__init__.py
git2py/gitlab.py
git2py-0.0.4.dist-info/LICENSE
git2py-0.0.4.dist-info/METADATA
git2py-0.0.4.dist-info/WHEEL
git2py-0.0.4.dist-info/top_level.txt
git2py-0.0.4.dist-info/RECORD
