Metadata-Version: 2.1
Name: git2py
Version: 0.0.4
Summary: Mapping git operation to a dict-like Data Object Layer
Home-page: https://github.com/i2mint/git2py
Author: OtoSense
License: apache-2.0
Platform: any
Requires-Dist: dol
Requires-Dist: py2store
Requires-Dist: hubcap
